eda_nijin-0.4.0.dist-info/METADATA
eda_nijin-0.4.0.dist-info/WHEEL
eda_nijin-0.4.0.dist-info/entry_points.txt
eda_nijin/.cli.py.swp
eda_nijin/__init__.py
eda_nijin/cli.py
eda_nijin-0.4.0.dist-info/RECORD
