Metadata-Version: 2.1
Name: eda-nijin
Version: 0.4.0
Summary: Default template for PDM package
Author-Email: heejin131 <journeyjean131@gmail.com>
License: MIT
Requires-Python: >=3.10
Requires-Dist: pandas>=2.2.3
Requires-Dist: president-speech>=0.9.1
Requires-Dist: typer>=0.15.1
